baolib/__init__.py
baolib/__main__.py
baolib/bao.py
baolib/baob.py
baolib/baod.py
baolib/options.py
baolib/_libs/libbao_amd64.h
baolib/_libs/libbao_amd64.so
baolib-0.1.7.dist-info/licenses/LICENSE
baolib-0.1.7.dist-info/METADATA
baolib-0.1.7.dist-info/WHEEL
baolib-0.1.7.dist-info/top_level.txt
baolib-0.1.7.dist-info/RECORD
